ripimage/__init__.py
ripimage/ripper.py
ripimage-0.1.0.dist-info/LICENSE
ripimage-0.1.0.dist-info/METADATA
ripimage-0.1.0.dist-info/WHEEL
ripimage-0.1.0.dist-info/top_level.txt
ripimage-0.1.0.dist-info/RECORD
