Metadata-Version: 2.1
Name: ripimage
Version: 0.1.0
Summary: library based on image-slicer, numpy and opencv to slice images
Home-page: UNKNOWN
Author: jagra26
Author-email: UNKNOWN
License: MIT
Platform: UNKNOWN
